[
  {
    "id": "pk_134",
    "building_id": "bld_2",
    "building_name": "431 Valley RD",
    "unit": "225",
    "guest_name": "Gil",
    "plan": "per_day_plan",
    "amount": 12.5,
    "start_date": "2026-04-04",
    "end_date": "2026-04-09",
    "car_brand": "Ford",
    "car_model": "Prius",
    "car_color": "Gold",
    "license_plate": "FYZ-2409",
    "email": "",
    "phone": "2159178700",
    "transaction_id": "ch_3Pf8G1SzchHybn60ncSOO2X",
    "payment_account": "Parking Elkins",
    "status": "active",
    "created": "2026-04-04"
  },
  {
    "id": "pk_133",
    "building_id": "bld_1",
    "building_name": "46 Township Line RD - Chelbourne Plaza",
    "unit": "112",
    "guest_name": "Damaris reyes",
    "plan": "20days",
    "amount": 46,
    "start_date": "2026-03-28",
    "end_date": "2026-04-17",
    "car_brand": "Ford",
    "car_model": "Transit",
    "car_color": "White",
    "license_plate": "5829787",
    "email": "",
    "phone": "8328826463",
    "transaction_id": "ch_3TYOLJcnowSlZAl0eBStrnS0",
    "payment_account": "Live ERA",
    "status": "active",
    "created": "2026-03-28"
  },
  {
    "id": "pk_132",
    "building_id": "bld_1",
    "building_name": "46 Township Line RD - Chelbourne Plaza",
    "unit": "112",
    "guest_name": "Damaris reyes",
    "plan": "20days",
    "amount": 46,
    "start_date": "2026-03-28",
    "end_date": "2026-04-17",
    "car_brand": "GMC",
    "car_model": "Denalli",
    "car_color": "Red",
    "license_plate": "5823666",
    "email": "",
    "phone": "8328826463",
    "transaction_id": "ch_3TYOLJcnowSlZAl0eBStPaRe",
    "payment_account": "Live ERA",
    "status": "active",
    "created": "2026-03-28"
  },
  {
    "id": "pk_131",
    "building_id": "bld_1",
    "building_name": "46 Township Line RD - Chelbourne Plaza",
    "unit": "112",
    "guest_name": "Damaris Reyes",
    "plan": "30days",
    "amount": 64,
    "start_date": "2026-03-21",
    "end_date": "2026-04-20",
    "car_brand": "Ram",
    "car_model": "3500 Dually",
    "car_color": "White",
    "license_plate": "RYK4911",
    "email": "",
    "phone": "8328826463",
    "transaction_id": "ch_3TYOLJcnowSlZAl0eBSt0uCz",
    "payment_account": "Live ERA",
    "status": "active",
    "created": "2026-03-21"
  },
  {
    "id": "pk_130",
    "building_id": "bld_2",
    "building_name": "431 Valley RD",
    "unit": "Rear",
    "guest_name": "Otar",
    "plan": "30days",
    "amount": 70,
    "start_date": "2026-03-19",
    "end_date": "2026-04-18",
    "car_brand": "Toyota",
    "car_model": "Prius",
    "car_color": "Gold",
    "license_plate": "MTK 0874",
    "email": "otootookh@gmail.com",
    "phone": "",
    "transaction_id": "ch_3TYOLl2SzchHybn60NbStCaP",
    "payment_account": "Parking Elkins",
    "status": "active",
    "created": "2026-03-19"
  },
  {
    "id": "pk_129",
    "building_id": "bld_1",
    "building_name": "46 Township Line RD - Chelbourne Plaza",
    "unit": "112",
    "guest_name": "Damaris reyes",
    "plan": "30days",
    "amount": 64,
    "start_date": "2026-03-19",
    "end_date": "2026-04-18",
    "car_brand": "Jeep",
    "car_model": "Galatiador",
    "car_color": "Blue",
    "license_plate": "278930",
    "email": "",
    "phone": "8328826463",
    "transaction_id": "ch_3TYOLJcnowSlZAl0eBStMuQy",
    "payment_account": "Live ERA",
    "status": "active",
    "created": "2026-03-19"
  },
  {
    "id": "pk_128",
    "building_id": "bld_4",
    "building_name": "7845 Montgomery",
    "unit": "5B",
    "guest_name": "Justin Krebs",
    "plan": "30days",
    "amount": 60,
    "start_date": "2026-03-11",
    "end_date": "2026-04-10",
    "car_brand": "Ford",
    "car_model": "Edge",
    "car_color": "Silver",
    "license_plate": "EGW D07",
    "email": "",
    "phone": "6054306888",
    "transaction_id": "ch_3Pf8G1CzchHexbnl0DlFunlgd",
    "payment_account": "Parking Elkins",
    "status": "active",
    "created": "2026-03-11"
  },
  {
    "id": "pk_127",
    "building_id": "bld_1",
    "building_name": "46 Township Line RD - Chelbourne Plaza",
    "unit": "122",
    "guest_name": "JOE MASALTA",
    "plan": "60days",
    "amount": 125,
    "start_date": "2026-03-06",
    "end_date": "2026-05-05",
    "car_brand": "Dodge",
    "car_model": "Ram",
    "car_color": "Silver",
    "license_plate": "VBB3835",
    "email": "",
    "phone": "2676447092",
    "transaction_id": "ch_3TYOLJcnowSlODMnntqol",
    "payment_account": "Live ERA",
    "status": "active",
    "created": "2026-03-06"
  },
  {
    "id": "pk_126",
    "building_id": "bld_1",
    "building_name": "46 Township Line RD - Chelbourne Plaza",
    "unit": "202",
    "guest_name": "Heather Shandler",
    "plan": "30days",
    "amount": 64,
    "start_date": "2026-02-24",
    "end_date": "2026-03-26",
    "car_brand": "Honda",
    "car_model": "CRV",
    "car_color": "Grey",
    "license_plate": "MPW-6424",
    "email": "",
    "phone": "5618009905",
    "transaction_id": "ch_3TYMPLJcnowSlx3eBKMsCl",
    "payment_account": "Live ERA",
    "status": "expired",
    "created": "2026-02-24"
  },
  {
    "id": "pk_125",
    "building_id": "bld_2",
    "building_name": "431 Valley RD",
    "unit": "Rear",
    "guest_name": "Otar",
    "plan": "30days",
    "amount": 70,
    "start_date": "2026-02-20",
    "end_date": "2026-03-22",
    "car_brand": "Toyota",
    "car_model": "Prius",
    "car_color": "Gold",
    "license_plate": "MTK 0874",
    "email": "otootookh@gmail.com",
    "phone": "",
    "transaction_id": "ch_3Pf8plGl1SzchHybnl60ParkingEul",
    "payment_account": "Parking Elkins",
    "status": "expired",
    "created": "2026-02-20"
  },
  {
    "id": "pk_124",
    "building_id": "bld_2",
    "building_name": "431 Valley RD",
    "unit": "MVJ 6627",
    "guest_name": "Davit",
    "plan": "30days",
    "amount": 70,
    "start_date": "2026-02-19",
    "end_date": "2026-03-21",
    "car_brand": "Toyota",
    "car_model": "Prius",
    "car_color": "Red",
    "license_plate": "MVJ 6627",
    "email": "devnosadze91@gmail.com",
    "phone": "",
    "transaction_id": "ch_3l2fhCCSzchHybn60NcSOO2X",
    "payment_account": "Parking Elkins",
    "status": "expired",
    "created": "2026-02-19"
  },
  {
    "id": "pk_123",
    "building_id": "bld_1",
    "building_name": "46 Township Line RD - Chelbourne Plaza",
    "unit": "330",
    "guest_name": "Tyler",
    "plan": "20days",
    "amount": 46,
    "start_date": "2026-01-23",
    "end_date": "2026-02-12",
    "car_brand": "Toyota",
    "car_model": "Camry",
    "car_color": "Black",
    "license_plate": "Q7F312F",
    "email": "",
    "phone": "8145331l3",
    "transaction_id": "ch_3St2ZJcnawSlZAl0avJhA6Y",
    "payment_account": "Live ERA",
    "status": "expired",
    "created": "2026-01-23"
  },
  {
    "id": "pk_122",
    "building_id": "bld_1",
    "building_name": "46 Township Line RD - Chelbourne Plaza",
    "unit": "208",
    "guest_name": "Laylaa Ahmad",
    "plan": "10days",
    "amount": 24,
    "start_date": "2026-01-20",
    "end_date": "2026-01-30",
    "car_brand": "Volkswagen",
    "car_model": "Tiguan",
    "car_color": "Black",
    "license_plate": "Kjg9l38",
    "email": "laylaaahmad@gmail.com",
    "phone": "",
    "transaction_id": "ch_3SmBLJcnawSlZAl0eBStrnS0",
    "payment_account": "Parking Elkins",
    "status": "expired",
    "created": "2026-01-20"
  },
  {
    "id": "pk_121",
    "building_id": "bld_2",
    "building_name": "431 Valley RD",
    "unit": "Rear",
    "guest_name": "Otar",
    "plan": "30days",
    "amount": 70,
    "start_date": "2026-01-20",
    "end_date": "2026-02-19",
    "car_brand": "Toyota",
    "car_model": "Prius",
    "car_color": "Gold",
    "license_plate": "MTK 0874",
    "email": "otootookh@gmail.com",
    "phone": "",
    "transaction_id": "ch_3SrjxoCSzchHybn60KfLx7Mu",
    "payment_account": "Parking Elkins",
    "status": "expired",
    "created": "2026-01-20"
  },
  {
    "id": "pk_120",
    "building_id": "bld_2",
    "building_name": "431 Valley RD",
    "unit": "MVJ 6627",
    "guest_name": "GIORGI",
    "plan": "30days",
    "amount": 70,
    "start_date": "2026-01-16",
    "end_date": "2026-02-15",
    "car_brand": "Toyota",
    "car_model": "Prius",
    "car_color": "Red",
    "license_plate": "MVJ 6627",
    "email": "devnosadze91@gmail.com",
    "phone": "",
    "transaction_id": "ch_3SqRMnCSzchHybn6lCYzmuQy",
    "payment_account": "Parking Elkins",
    "status": "expired",
    "created": "2026-01-16"
  },
  {
    "id": "pk_119",
    "building_id": "bld_2",
    "building_name": "431 Valley RD",
    "unit": "MST 8012",
    "guest_name": "GIORGI",
    "plan": "30days",
    "amount": 70,
    "start_date": "2026-01-15",
    "end_date": "2026-02-14",
    "car_brand": "Toyota",
    "car_model": "Prius",
    "car_color": "Blue",
    "license_plate": "MST8012",
    "email": "devnosadze91@gmail.com",
    "phone": "",
    "transaction_id": "ch_3Sq23pCSzchHybn6lsNQqFWJ",
    "payment_account": "Parking Elkins",
    "status": "expired",
    "created": "2026-01-15"
  },
  {
    "id": "pk_118",
    "building_id": "bld_2",
    "building_name": "431 Valley RD",
    "unit": "Rear",
    "guest_name": "Otar",
    "plan": "30days",
    "amount": 70,
    "start_date": "2025-12-19",
    "end_date": "2026-01-18",
    "car_brand": "Toyota",
    "car_model": "Prius",
    "car_color": "Gold",
    "license_plate": "MTK 0874",
    "email": "otootookh@gmail.com",
    "phone": "",
    "transaction_id": "ch_3SgGjqCSzchHybn60ZxdWm0b",
    "payment_account": "Parking Elkins",
    "status": "expired",
    "created": "2025-12-19"
  },
  {
    "id": "pk_117",
    "building_id": "bld_3",
    "building_name": "278 N. Keswick",
    "unit": "225",
    "guest_name": "Sigalit",
    "plan": "per_day_plan",
    "amount": 0.5,
    "start_date": "2025-12-08",
    "end_date": "2025-12-13",
    "car_brand": "fghjk",
    "car_model": "Test",
    "car_color": "Black",
    "license_plate": "jhgfds",
    "email": "",
    "phone": "2159178700",
    "transaction_id": "ch_3SdFoCSzchHybn6lmGMuOb8",
    "payment_account": "Parking Elkins",
    "status": "expired",
    "created": "2025-12-08"
  },
  {
    "id": "pk_116",
    "building_id": "bld_3",
    "building_name": "278 N. Keswick",
    "unit": "225",
    "guest_name": "Shlomo",
    "plan": "per_day_plan",
    "amount": 0.5,
    "start_date": "2025-12-09",
    "end_date": "2025-12-14",
    "car_brand": "ngfdvs",
    "car_model": "HHHJ",
    "car_color": "z cx",
    "license_plate": "",
    "email": "",
    "phone": "2159178700",
    "transaction_id": "ch_3Sdf4pCSzchHybn6l8MutUU",
    "payment_account": "Parking Elkins",
    "status": "expired",
    "created": "2025-12-09"
  },
  {
    "id": "pk_115",
    "building_id": "bld_3",
    "building_name": "278 N. Keswick",
    "unit": "225",
    "guest_name": "Gil",
    "plan": "per_day_plan",
    "amount": 0.5,
    "start_date": "2025-12-01",
    "end_date": "2025-12-06",
    "car_brand": "ngfdvs",
    "car_model": "bvcx",
    "car_color": "bvfd",
    "license_plate": "sCD",
    "email": "",
    "phone": "2159178700",
    "transaction_id": "ch_3SZhr2CSzchHybn60lru7N00",
    "payment_account": "Parking Elkins",
    "status": "expired",
    "created": "2025-12-01"
  }
]
